vision/__init__.py
vision/common.py
vision/roblang.py
vision/socketfunc.py
vision/vision.py
vision/visionfunc.py
kais_kit_vision_02-0.0.1.dist-info/METADATA
kais_kit_vision_02-0.0.1.dist-info/WHEEL
kais_kit_vision_02-0.0.1.dist-info/top_level.txt
kais_kit_vision_02-0.0.1.dist-info/RECORD
